knuverse/__init__.py
knuverse/knufactor.py
knuverse/data/__init__.py
knuverse/data/url.py
knuverse-1.0.7.dist-info/DESCRIPTION.rst
knuverse-1.0.7.dist-info/METADATA
knuverse-1.0.7.dist-info/RECORD
knuverse-1.0.7.dist-info/WHEEL
knuverse-1.0.7.dist-info/metadata.json
knuverse-1.0.7.dist-info/top_level.txt
