Metadata-Version: 2.0
Name: knuverse
Version: 1.0.7
Summary: A Python SDK for interfacing with KnuVerse Cloud APIs
Home-page: https://github.com/KnuVerse/knuverse-sdk-python
Author: KnuVerse
Author-email: support@knuverse.com
License: MIT
Keywords: api sdk knuverse cloud voice authentication audiopin audiopass
Platform: UNKNOWN
Classifier: Development Status :: 3 - Alpha
Classifier: Intended Audience :: Developers
Classifier: Topic :: Software Development :: Build Tools
Classifier: License :: OSI Approved :: MIT License
Classifier: Programming Language :: Python :: 2.7
Classifier: Programming Language :: Python :: 3
Classifier: Programming Language :: Python :: 3.3
Classifier: Programming Language :: Python :: 3.4
Classifier: Programming Language :: Python :: 3.5
Requires-Dist: requests
